README.rst
setup.py
Kerapu.egg-info/PKG-INFO
Kerapu.egg-info/SOURCES.txt
Kerapu.egg-info/dependency_links.txt
Kerapu.egg-info/entry_points.txt
Kerapu.egg-info/requires.txt
Kerapu.egg-info/top_level.txt
kerapu/Kerapu.py
kerapu/__init__.py
kerapu/application/KerapuApplication.py
kerapu/application/__init__.py
kerapu/application/kerapu.py
kerapu/boom/AttribuutGroep.py
kerapu/boom/BeslisRegel.py
kerapu/boom/ZorgProductGroep.py
kerapu/boom/ZorgProductGroepVersie.py
kerapu/boom/__init__.py
kerapu/boom/attribuut/Attribuut.py
kerapu/boom/attribuut/Attribuut12.py
kerapu/boom/attribuut/Attribuut21.py
kerapu/boom/attribuut/__init__.py
kerapu/boom/attribuut_groep_koppeling/AttribuutGroepKoppeling.py
kerapu/boom/attribuut_groep_koppeling/AttribuutGroepKoppeling2.py
kerapu/boom/attribuut_groep_koppeling/__init__.py
kerapu/boom/boom_parameter/BehandelKlasse.py
kerapu/boom/boom_parameter/BoomParameter.py
kerapu/boom/boom_parameter/DiagnoseCluster.py
kerapu/boom/boom_parameter/DiagnoseCode.py
kerapu/boom/boom_parameter/Geslacht.py
kerapu/boom/boom_parameter/Leeftijd.py
kerapu/boom/boom_parameter/SpecialismeCluster.py
kerapu/boom/boom_parameter/SpecialismeCode.py
kerapu/boom/boom_parameter/ZorgActiviteitCluster.py
kerapu/boom/boom_parameter/ZorgActiviteitCode.py
kerapu/boom/boom_parameter/ZorgInstellingCode.py
kerapu/boom/boom_parameter/ZorgTypeCode.py
kerapu/boom/boom_parameter/ZorgVraagCluster.py
kerapu/boom/boom_parameter/ZorgVraagCode.py
kerapu/boom/boom_parameter/__init__.py
kerapu/command/ShredderCommand.py
kerapu/command/TestsetShredderCommand.py
kerapu/command/__init__.py
kerapu/lbz/Diagnose.py
kerapu/lbz/Patient.py
kerapu/lbz/Specialisme.py
kerapu/lbz/Subtraject.py
kerapu/lbz/ZorgActiviteit.py
kerapu/lbz/ZorgInstelling.py
kerapu/lbz/ZorgType.py
kerapu/lbz/ZorgVraag.py
kerapu/lbz/__init__.py
kerapu/shredder/BoomBestandenShredder.py
kerapu/shredder/ReferentieShredder.py
kerapu/shredder/Shredder.py
kerapu/shredder/__init__.py
kerapu/style/KerapuStyle.py
kerapu/style/__init__.py