Metadata-Version: 1.1
Name: Kerapu
Version: 2.0.3
Summary: Een implementatie van de grouper
Home-page: https://github.com/SetBased/py-kerapu
Author: Paul Water
Author-email: p.r.water@setbased.nl
License: MIT
Keywords: DBC Grouper
Platform: UNKNOWN
Classifier: Development Status :: 5 - Production/Stable
Classifier: Intended Audience :: Developers
Classifier: License :: OSI Approved :: MIT License
Classifier: Natural Language :: Dutch
Classifier: Operating System :: OS Independent
Classifier: Programming Language :: Python :: 3
Classifier: Programming Language :: Python :: 3.6
Classifier: Programming Language :: Python :: 3.7
